model_monitoring_package/__init__.py
model_monitoring_package-0.0.1.dist-info/METADATA
model_monitoring_package-0.0.1.dist-info/WHEEL
model_monitoring_package-0.0.1.dist-info/top_level.txt
model_monitoring_package-0.0.1.dist-info/RECORD
