Metadata-Version: 2.1
Name: model-monitoring-package
Version: 0.0.1
Summary: A very basic monitoring package
Author: Ritik Saxena
Author-email: ritiksaxena90@gmail.com
License: UNKNOWN
Keywords: package
Platform: UNKNOWN
Requires-Dist: pandas
Requires-Dist: streamlit
Requires-Dist: datetime
Requires-Dist: numpy
